CHANGELOG.txt
LICENCE.txt
MANIFEST.in
README.txt
setup.py
djpthon/__init__.py
djpython.egg-info/PKG-INFO
djpython.egg-info/SOURCES.txt
djpython.egg-info/dependency_links.txt
djpython.egg-info/top_level.txt